orchestrate/__init__.py
orchestrate/common.py
orchestrate/version.py
orchestrate/__pycache__/__init__.cpython-36.pyc
orchestrate/__pycache__/common.cpython-36.pyc
orchestrate/__pycache__/version.cpython-36.pyc
orchestrate/core/__init__.py
orchestrate/core/__main__.py
orchestrate/core/cement_utils.py
orchestrate/core/exceptions.py
orchestrate/core/main.py
orchestrate/core/paths.py
orchestrate/core/__pycache__/__init__.cpython-36.pyc
orchestrate/core/__pycache__/exceptions.cpython-36.pyc
orchestrate/core/__pycache__/main.cpython-36.pyc
orchestrate/core/__pycache__/paths.cpython-36.pyc
orchestrate/core/autoscaling/__init__.py
orchestrate/core/autoscaling/service.py
orchestrate/core/autoscaling/__pycache__/__init__.cpython-36.pyc
orchestrate/core/autoscaling/__pycache__/service.cpython-36.pyc
orchestrate/core/aws/__init__.py
orchestrate/core/aws/service.py
orchestrate/core/aws/__pycache__/__init__.cpython-36.pyc
orchestrate/core/aws/__pycache__/service.cpython-36.pyc
orchestrate/core/cloudformation/__init__.py
orchestrate/core/cloudformation/service.py
orchestrate/core/cluster/__init__.py
orchestrate/core/cluster/context.py
orchestrate/core/cluster/errors.py
orchestrate/core/cluster/object.py
orchestrate/core/cluster/service.py
orchestrate/core/cluster/__pycache__/__init__.cpython-36.pyc
orchestrate/core/cluster/__pycache__/context.cpython-36.pyc
orchestrate/core/cluster/__pycache__/errors.cpython-36.pyc
orchestrate/core/cluster/__pycache__/object.cpython-36.pyc
orchestrate/core/cluster/__pycache__/service.cpython-36.pyc
orchestrate/core/cluster_metadata/__init__.py
orchestrate/core/cluster_metadata/errors.py
orchestrate/core/cluster_metadata/service.py
orchestrate/core/cluster_metadata/__pycache__/__init__.cpython-36.pyc
orchestrate/core/cluster_metadata/__pycache__/errors.cpython-36.pyc
orchestrate/core/cluster_metadata/__pycache__/service.cpython-36.pyc
orchestrate/core/custom_cluster/__init__.py
orchestrate/core/custom_cluster/service.py
orchestrate-0.7.0.dist-info/LICENSE.md
orchestrate-0.7.0.dist-info/METADATA
orchestrate-0.7.0.dist-info/WHEEL
orchestrate-0.7.0.dist-info/entry_points.txt
orchestrate-0.7.0.dist-info/top_level.txt
orchestrate-0.7.0.dist-info/RECORD
