Metadata-Version: 2.1
Name: orchestrate
Version: 0.7.0
Summary: SigOpt Orchestrate Client
Home-page: https://sigopt.com/docs/orchestrate
Author: SigOpt
Author-email: support@sigopt.com
License: Apache License 2.0
Platform: UNKNOWN
Classifier: Development Status :: 3 - Alpha
Classifier: Intended Audience :: Developers
Classifier: Intended Audience :: System Administrators
Classifier: License :: OSI Approved :: Apache Software License
Classifier: Natural Language :: English
Classifier: Operating System :: MacOS
Classifier: Operating System :: POSIX :: Linux
Classifier: Programming Language :: Python
Classifier: Programming Language :: Python :: 2
Classifier: Programming Language :: Python :: 2.7
Classifier: Programming Language :: Python :: 3
Classifier: Programming Language :: Python :: 3.6
Classifier: Programming Language :: Python :: 3.7
Classifier: Topic :: Software Development
Requires-Python: >=2.7.9,!=3.0.*,!=3.1.*,!=3.2.*,!=3.3.*,!=3.4.*,!=3.5.*
Requires-Dist: awscli (==1.16.14)
Requires-Dist: botocore (==1.12.4)
Requires-Dist: boto3 (==1.9.4)
Requires-Dist: cement (==2.10.12)
Requires-Dist: colorama (==0.3.9)
Requires-Dist: docker (==3.4.1)
Requires-Dist: futures
Requires-Dist: kubernetes (==8.0.0)
Requires-Dist: pystache (==0.5.4)
Requires-Dist: PyYAML (==3.13)
Requires-Dist: requests (==2.19.1)
Requires-Dist: sigopt (<6.0.0,>=5.0.0)
Requires-Dist: six (==1.11.0)
Provides-Extra: dev
Requires-Dist: flake8 (==3.5.0) ; extra == 'dev'
Requires-Dist: isort (==4.3.4) ; extra == 'dev'
Requires-Dist: mock (<3.0.0,>=2.0.0) ; extra == 'dev'
Requires-Dist: nose (==1.3.7) ; extra == 'dev'
Requires-Dist: numpy (<2.0.0,>=1.15.0) ; extra == 'dev'
Requires-Dist: pylint (==1.9.1) ; extra == 'dev'
Requires-Dist: pytest (==3.6.1) ; extra == 'dev'
Requires-Dist: setuptools (<41.0.0,>=40.0.0) ; extra == 'dev'
Requires-Dist: twine (<2.0.0,>=1.11.0) ; extra == 'dev'
